Workbook

Sheet Variables
A1: Month | B1: Week | C1: Year | D1: Outreachs | E1: Scheduled 1:1 | F1: Scheduling rate | G1: No show | H1: 1:1 rate | I1: Deals | J1: Deal rate
A2: October | B2: 40 | C2: 2025 | D2: =COUNTIFS('2025.10'!I:I,">="&DATE(2025,10,1),'2025.10'!I:I,"<="&DATE(2025,10,3)) -> 354 | E2: =COUNTIFS('2025.10'!I:I,">="&DATE(2025,10,1),'2025.10'!I:I,"<="&DATE(2025,10,3), '2025.10'!L:L, "Call Done")+G2 -> 25 | F2: =E2/D2 -> 0.070621469 | G2: =COUNTIFS('2025.10'!I:I,">="&DATE(2025,10,1),'2025.10'!I:I,"<="&DATE(2025,10,3), '2025.10'!L:L, "No show") -> 13 | H2: =(E2-G2)/E2 -> 0.48 | I2: 0 | J2: =I2/E2 -> 0
A3: October | B3: 41 | C3: 2025 | D3: =COUNTIFS('2025.10'!I:I,">="&DATE(2025,10,6),'2025.10'!I:I,"<="&DATE(2025,10,10)) -> 557 | E3: =COUNTIFS('2025.10'!I:I,">="&DATE(2025,10,6),'2025.10'!I:I,"<="&DATE(2025,10,10), '2025.10'!L:L, "Call Done")+G3 -> 43 | F3: =E3/D3 -> 0.077199282 | G3: =COUNTIFS('2025.10'!I:I,">="&DATE(2025,10,6),'2025.10'!I:I,"<="&DATE(2025,10,10), '2025.10'!L:L, "No show") -> 20 | H3: =(E3-G3)/E3 -> 0.53488372 | I3: 0 | J3: =I3/E3 -> 0
A4: October | B4: 42 | C4: 2025 | D4: =COUNTIFS('2025.10'!I:I,">="&DATE(2025,10,13),'2025.10'!I:I,"<="&DATE(2025,10,17)) -> 454 | E4: =COUNTIFS('2025.10'!I:I,">="&DATE(2025,10,13),'2025.10'!I:I,"<="&DATE(2025,10,17), '2025.10'!L:L, "Call Done")+G4 -> 15 | F4: =E4/D4 -> 0.033039648 | G4: =COUNTIFS('2025.10'!I:I,">="&DATE(2025,10,13),'2025.10'!I:I,"<="&DATE(2025,10,17), '2025.10'!L:L, "No show") -> 10 | H4: =(E4-G4)/E4 -> 0.33333333 | I4: 0 | J4: =I4/E4 -> 0
A5: October | B5: 43 | C5: 2025 | D5: =COUNTIFS('2025.10'!I:I,">="&DATE(2025,10,20),'2025.10'!I:I,"<="&DATE(2025,10,24)) -> 183 | E5: =COUNTIFS('2025.10'!I:I,">="&DATE(2025,10,20),'2025.10'!I:I,"<="&DATE(2025,10,24),'2025.10'!L:L, "Call Done")+G5 -> 12 | F5: =E5/D5 -> 0.06557377 | G5: =COUNTIFS('2025.10'!I:I,">="&DATE(2025,10,20),'2025.10'!I:I,"<="&DATE(2025,10,24),'2025.10'!L:L, "No show") -> 3 | H5: =(E5-G5)/E5 -> 0.75 | I5: 0 | J5: =I5/E5 -> 0
A6: October | B6: 44 | C6: 2025 | D6: =COUNTIFS('2025.10'!I:I,">="&DATE(2025,10,27),'2025.10'!I:I,"<="&DATE(2025,10,31)) -> 476 | E6: =COUNTIFS('2025.10'!I:I,">="&DATE(2025,10,27),'2025.10'!I:I,"<="&DATE(2025,10,31), '2025.10'!L:L, "Call Done")+G6 -> 17 | F6: =E6/D6 -> 0.035714286 | G6: =COUNTIFS('2025.10'!I:I,">="&DATE(2025,10,27),'2025.10'!I:I,"<="&DATE(2025,10,31), '2025.10'!L:L, "No show") -> 8 | H6: =(E6-G6)/E6 -> 0.52941176 | I6: 0 | J6: =I6/E6 -> 0
A7: November | B7: 45 | C7: 2025 | D7: =COUNTIFS('2025.11'!I:I,">="&DATE(2025,11,3),'2025.11'!I:I,"<="&DATE(2025,11,7)) -> 303 | E7: =COUNTIFS('2025.11'!I:I,">="&DATE(2025,11,3),'2025.11'!I:I,"<="&DATE(2025,11,7), '2025.11'!L:L, "Call Done")+G7 -> 13 | F7: =E7/D7 -> 0.04290429 | G7: =COUNTIFS('2025.11'!I:I,">="&DATE(2025,11,3),'2025.11'!I:I,"<="&DATE(2025,11,7), '2025.11'!L:L, "No show") -> 8 | H7: =(E7-G7)/E7 -> 0.38461538 | I7: 0 | J7: =I7/E7 -> 0
A8: November | B8: 46 | C8: 2025 | D8: =COUNTIFS('2025.11'!I:I,">="&DATE(2025,11,10),'2025.11'!I:I,"<="&DATE(2025,11,14)) -> 475 | E8: =COUNTIFS('2025.11'!I:I,">="&DATE(2025,11,10),'2025.11'!I:I,"<="&DATE(2025,11,14), '2025.11'!L:L, "Call Done")+G8 -> 3 | F8: =E8/D8 -> 0.0063157895 | G8: =COUNTIFS('2025.11'!I:I,">="&DATE(2025,11,10),'2025.11'!I:I,"<="&DATE(2025,11,14), '2025.11'!L:L, "No show") -> 1 | H8: =(E8-G8)/E8 -> 0.66666667 | I8: 0 | J8: =I8/E8 -> 0
A9: November | B9: 47 | C9: 2025
A10: November | B10: 48 | C10: 2025
C11: 2025
C12: 2025
C13: 2025
C14: 2025
C15: 2025

Sheet 2025.10
C6: BNI Chapter | D6: Address | E6: Member Name | F6: Company | G6: Profession | H6: Phone | I6: Contact | J6: Sales Executive | K6: SDR | L6: Status
C7: BNI Vision | D7: Kendall, FL, 33173 | E7: Alejandro Jordan | F7: ESQ.title | Real Estate Law | G7: Real Estate Law | H7: 305-606-3855 | I7: =DATE(2025, 10, 1) -> 45931 | J7: Gabriel Khalil | K7: Gabriel Khalil
C8: BNI Vision | D8: Kendall, FL, 33174 | E8: Angel F. Fernandez | F8: Fernandez-Bergnes & Assoc PA | G8: Tax Advisor | H8: 305-648-7100 | I8: =DATE(2025, 10, 1) -> 45931 | J8: Gabriel Khalil | K8: Gabriel Khalil
C9: BNI Vision | D9: Kendall, FL, 33175 | E9: Christina Geeza | F9: Corporate Attorney | G9: Company Formation | H9: 3055679000 | I9: =DATE(2025, 10, 1) -> 45931 | J9: Gabriel Khalil | K9: Gabriel Khalil
C10: BNI Vision | D10: Kendall, FL, 33176 | E10: Christopher Gabriel | F10: Smart Business Solutions Consultation Corp | G10: IT Consultants | H10: 3055030873 | I10: =DATE(2025, 10, 1) -> 45931 | J10: Gabriel Khalil | K10: Gabriel Khalil
C11: BNI Vision | D11: Kendall, FL, 33177 | E11: Dmitriy Smirnov | F11: Top Lead marketing | G11: Web Design | H11: 941-350-2656 | I11: =DATE(2025, 10, 1) -> 45931 | J11: Gabriel Khalil | K11: Gabriel Khalil
C12: BNI Vision | D12: Kendall, FL, 33178 | E12: Elisabeth Leyva Fernandez | F12: Leyva Law Office P.A. | G12: Family Law | H12: 3059652452 | I12: =DATE(2025, 10, 1) -> 45931 | J12: Gabriel Khalil | K12: Gabriel Khalil
C13: BNI Vision | D13: Kendall, FL, 33179 | E13: Gabriela Dominguez | F13: Avante Insurance Agency Inc. | G13: Property & Casualty Insurance | H13: 305-812-7605 | I13: =DATE(2025, 10, 1) -> 45931 | J13: Gabriel Khalil | K13: Gabriel Khalil
C14: BNI Vision | D14: Kendall, FL, 33180 | E14: Gina Chevallier | F14: LAW OFFICE OF GINA R. CHEVALLIER | G14: Estate Planning Law | H14: (305) 974-1490 | I14: =DATE(2025, 10, 1) -> 45931 | J14: Gabriel Khalil | K14: Gabriel Khalil
C15: BNI Vision | D15: Kendall, FL, 33181 | E15: Leodan Leonel Leon Naranjo | F15: BERKSHIRE HATHAWAY | G15: Residential Real Estate Agent | H15: 7869052481 | I15: =DATE(2025, 10, 1) -> 45931 | J15: Gabriel Khalil | K15: Gabriel Khalil
C16: BNI Vision | D16: Kendall, FL, 33182 | E16: Mario Louis | F16: Law Offices of M.J. Louis P.A. | G16: Personal Injury Law | H16: 305-377-9646 | I16: =DATE(2025, 10, 1) -> 45931 | J16: Gabriel Khalil | K16: Gabriel Khalil
C17: BNI Vision | D17: Kendall, FL, 33183 | E17: Raul Isern | F17: Atlantic Family Wealth | G17: Financial Advisor | H17: 305-222-0977 | I17: =DATE(2025, 10, 1) -> 45931 | J17: Gabriel Khalil | K17: Gabriel Khalil
C18: BNI Vision | D18: Kendall, FL, 33184 | E18: Simone Da Silva | F18: Bright Lighthouse Insurance | G18: Health Insurance | H18: 7862771870 | I18: =DATE(2025, 10, 1) -> 45931 | J18: Gabriel Khalil | K18: Gabriel Khalil
C19: BNI Connectify | D19: West Kendall, FL, 33185 | E19: Abraham Valera | F19: Reliable Choice Insurance | G19: Property & Casualty Insurance | H19: 305 299 4155 | I19: =DATE(2025, 10, 1) -> 45931 | J19: Gabriel Khalil | K19: Gabriel Khalil | L19: Out of pipe
C20: BNI Connectify | D20: West Kendall, FL, 33186 | E20: Ashley Brosky | F20: Luxe Properties | G20: Residential Real Estate Agent | H20: 305-788-3720 | I20: =DATE(2025, 10, 1) -> 45931 | J20: Gabriel Khalil | K20: Gabriel Khalil
C21: BNI Connectify | D21: West Kendall, FL, 33187 | E21: Barbara Rancano | F21: AirCool Florida | G21: HVAC - Heating & Air | H21: 305-254-8330 | I21: =DATE(2025, 10, 1) -> 45931 | J21: Gabriel Khalil | K21: Gabriel Khalil | L21: No show
C22: BNI Connectify | D22: West Kendall, FL, 33188 | E22: Darren Price | F22: Affix Handyman Solutions LLC | G22: Handyman | H22: 7862233003 | I22: =DATE(2025, 10, 1) -> 45931 | J22: Gabriel Khalil | K22: Gabriel Khalil | L22: Out of pipe
C23: BNI Connectify | D23: West Kendall, FL, 33189 | E23: Hope Khan | F23: The Closing Table of Florida | G23: Title Services | H23: 7865426287 | I23: =DATE(2025, 10, 1) -> 45931 | J23: Gabriel Khalil | K23: Gabriel Khalil
C24: BNI Connectify | D24: West Kendall, FL, 33190 | E24: Joseph Morana | F24: Paw-Fect Home Inspections | G24: Home Inspection | H24: 786-702-9160 | I24: =DATE(2025, 10, 1) -> 45931 | J24: Gabriel Khalil | K24: Gabriel Khalil
C25: BNI Connectify | D25: West Kendall, FL, 33191 | E25: Juan Ignacio Caffini | F25: HandyPro - South Miami | G25: Builder/General Contractor | H25: 786 205 8961 | I25: =DATE(2025, 10, 1) -> 45931 | J25: Gabriel Khalil | K25: Gabriel Khalil | L25: No show
C26: BNI Connectify | D26: West Kendall, FL, 33192 | E26: Michael Moreira | F26: Warrior Law Group | G26: Personal Injury Law | H26: 13059169123 | I26: =DATE(2025, 10, 1) -> 45931 | J26: Gabriel Khalil | K26: Gabriel Khalil
C27: BNI Connectify | D27: West Kendall, FL, 33193 | E27: Nicholas Iglesias | F27: Dade Mortgage Solutions LLC | G27: Residential Mortgages | H27: 3053904382 | I27: =DATE(2025, 10, 1) -> 45931 | J27: Gabriel Khalil | K27: Gabriel Khalil
C28: BNI Connectify | D28: West Kendall, FL, 33194 | E28: Shaun Judy | F28: Dade Pest Solutions | G28: Pest Control | H28: 3053305565 | I28: =DATE(2025, 10, 1) -> 45931 | J28: Gabriel Khalil | K28: Gabriel Khalil
C29: BNI Connectify | D29: West Kendall, FL, 33195 | E29: Stephanie Acevedo | F29: Stellar Public Adjusting Services | G29: Insurance Adjuster | H29: 17862538975 | I29: =DATE(2025, 10, 1) -> 45931 | J29: Gabriel Khalil | K29: Gabriel Khalil | L29: On hold
C30: BNI Virtual Success | D30: Pinecrest, FL, 33156 | E30: Alejandro Velez | F30: VIA Lawyers | G30: Business Law | H30: 3054251565 | I30: =DATE(2025, 10, 1) -> 45931 | J30: Gabriel Khalil | K30: Gabriel Khalil
C31: BNI Virtual Success | D31: Pinecrest, FL, 33157 | E31: Jason Wright | F31: PS Lending | G31: Residential Mortgages | H31: 7862106388 | I31: =DATE(2025, 10, 1) -> 45931 | J31: Gabriel Khalil | K31: Gabriel Khalil | L31: Call Done
C32: BNI Virtual Success | D32: Pinecrest, FL, 33158 | E32: Joey Joseph | F32: Dohan CPA | G32: Certified Public Accountant (CPA) | H32: 3059267315 | I32: =DATE(2025, 10, 1) -> 45931 | J32: Gabriel Khalil | K32: Gabriel Khalil
C33: BNI Virtual Success | D33: Pinecrest, FL, 33159 | E33: Justine Ochoa | F33: IHT Wealth Management | G33: Financial Advisor | H33: 3123341336 | I33: =DATE(2025, 10, 1) -> 45931 | J33: Gabriel Khalil | K33: Gabriel Khalil
C34: BNI Virtual Success | D34: Pinecrest, FL, 33160 | E34: Karla Jaimes | F34: EXP Realty | G34: Residential Real Estate Agent | H34: 9413506909 | I34: =DATE(2025, 10, 1) -> 45931 | J34: Gabriel Khalil | K34: Gabriel Khalil
C35: BNI Virtual Success | D35: Pinecrest, FL, 33161 | E35: Katie FitzGerald | F35: KFitz Consulting | G35: Marketing Consultant | H35: (786) 338-8058 | I35: =DATE(2025, 10, 1) -> 45931 | J35: Gabriel Khalil | K35: Gabriel Khalil
C36: BNI Virtual Success | D36: Pinecrest, FL, 33162 | E36: Michael Garcia | F36: RESF | G36: Commercial Real Estate | H36: 3052508297 | I36: =DATE(2025, 10, 1) -> 45931 | J36: Gabriel Khalil | K36: Gabriel Khalil
C37: BNI Virtual Success | D37: Pinecrest, FL, 33163 | E37: Ricardo Alonso | F37: Atesa Risk Advisors | G37: Property & Casualty Insurance | H37: 3055014845 | I37: =DATE(2025, 10, 1) -> 45931 | J37: Gabriel Khalil | K37: Gabriel Khalil
C38: BNI Virtual Success | D38: Pinecrest, FL, 33164 | E38: Roberto Fernandez | F38: Dania S. Fernandez and Associates P.A. | G38: Real Estate Law | H38: 7868977461 | I38: =DATE(2025, 10, 1) -> 45931 | J38: Gabriel Khalil | K38: Gabriel Khalil
C39: BNI Virtual Success | D39: Pinecrest, FL, 33165 | E39: Tatiana Cardoso | F39: N/A | G39: Personal Injury Law | H39: 7864129511 | I39: =DATE(2025, 10, 1) -> 45931 | J39: Gabriel Khalil | K39: Gabriel Khalil
C40: BNI Virtual Success | D40: Pinecrest, FL, 33166 | E40: Victor Castillo | F40: Castle Inspections | G40: Home Inspection | H40: 786-340-1500 | I40: =DATE(2025, 10, 1) -> 45931 | J40: Gabriel Khalil | K40: Gabriel Khalil
C41: BNI Virtual Success | D41: Pinecrest, FL, 33167 | E41: Will Bradwell | F41: Dade Local | G41: Print Advertising | H41: 7864578993 | I41: =DATE(2025, 10, 1) -> 45931 | J41: Gabriel Khalil | K41: Gabriel Khalil
C42: BNI Business Hub | D42: Pinecrest, FL, 33156 | E42: Agatha Landaetta | F42: The Key To Insurance, LLC | G42: Property & Casualty Insurance | H42: 7864614880 | I42: =DATE(2025, 10, 1) -> 45931 | J42: Gabriel Khalil | K42: Gabriel Khalil | L42: No show
C43: BNI Business Hub | D43: Pinecrest, FL, 33157 | E43: Alejandro Benavides | F43: HomeTeam | G43: Home Inspection | H43: 3057982085 | I43: =DATE(2025, 10, 1) -> 45931 | J43: Gabriel Khalil | K43: Gabriel Khalil
C44: BNI Business Hub | D44: Pinecrest, FL, 33158 | E44: Alex Martinez | F44: Alex A Martínez PA | G44: Estate Planning Law | H44: 3053799600 | I44: =DATE(2025, 10, 1) -> 45931 | J44: Gabriel Khalil | K44: Gabriel Khalil
C45: BNI Business Hub | D45: Pinecrest, FL, 33159 | E45: Arseni Kusakin | F45: Aigen Injury Law | G45: Personal Injury Law | H45: 19173404037 | I45: =DATE(2025, 10, 1) -> 45931 | J45: Gabriel Khalil | K45: Gabriel Khalil
C46: BNI Business Hub | D46: Pinecrest, FL, 33160 | E46: Claudia Sanchez | F46: South Florida Home Lending | G46: Residential Mortgages | H46: 7868974668 | I46: =DATE(2025, 10, 1) -> 45931 | J46: Gabriel Khalil | K46: Gabriel Khalil
C47: BNI Business Hub | D47: Pinecrest, FL, 33161 | E47: Elaine Perez | F47: The Elaine Group, Inc. | G47: Residential Real Estate Agent | H47: 786.287.4344 | I47: =DATE(2025, 10, 1) -> 45931 | J47: Gabriel Khalil | K47: Gabriel Khalil
C48: BNI Business Hub | D48: Pinecrest, FL, 33162 | E48: Evandro Gois | F48: EXPERTNESS TRANSLATIONS | G48: Translator/Language Services | H48: 7864401430 | I48: =DATE(2025, 10, 1) -> 45931 | J48: Gabriel Khalil | K48: Gabriel Khalil
C49: BNI Business Hub | D49: Pinecrest, FL, 33163 | E49: Jadon Apruzzese | F49: USHealth Advisors | G49: Health & Wellness (Other) | H49: 5179773619 | I49: =DATE(2025, 10, 1) -> 45931 | J49: Gabriel Khalil | K49: Gabriel Khalil
C50: BNI Business Hub | D50: Pinecrest, FL, 33164 | E50: Janet Stubbs | F50: Alex A Martinez, P.A | G50: Real Estate Law | H50: 7863067692 | I50: =DATE(2025, 10, 1) -> 45931 | J50: Gabriel Khalil | K50: Gabriel Khalil | L50: Call Done
C51: BNI Business Hub | D51: Pinecrest, FL, 33165 | E51: Jeannie Inchausti | F51: Ocean Bank | G51: Banking Services | H51: 17865465339 | I51: =DATE(2025, 10, 1) -> 45931 | J51: Gabriel Khalil | K51: Gabriel Khalil | L51: On hold
C52: BNI Business Hub | D52: Pinecrest, FL, 33166 | E52: Pedro Silva | F52: Verdeja and Alvarez, LLP | G52: Certified Public Accountant (CPA) | H52: 3059799199 | I52: =DATE(2025, 10, 1) -> 45931 | J52: Gabriel Khalil | K52: Gabriel Khalil
C53: BNI Business Hub | D53: Pinecrest, FL, 33167 | E53: Pedro Salim | F53: Pedro L. Salim Law Firm | G53: Immigration Law | H53: 305-306-6000 | I53: =DATE(2025, 10, 1) -> 45931 | J53: Gabriel Khalil | K53: Gabriel Khalil
C54: BNI Business Hub | D54: Pinecrest, FL, 33168 | E54: Stephany Antuche | F54: Portalatin Business Law Firm LLC | G54: Business Law | H54: (754) 314-9965 | I54: =DATE(2025, 10, 1) -> 45931 | J54: Gabriel Khalil | K54: Gabriel Khalil | L54: Call Done
C55: BNI Keys Elite | D55: 101925 Overseas Highway, Key Largo, FL, 33037 | E55: Alan Benavides | F55: HomeTeam Inspection Service | G55: Home Inspection | H55: 7867673582 | I55: =DATE(2025, 10, 1) -> 45931 | J55: Gabriel Khalil | K55: Gabriel Khalil
C56: BNI Keys Elite | D56: 101926 Overseas Highway, Key Largo, FL, 33037 | E56: Christine Del Valle | F56: National Trust Title Services | G56: Title Services | H56: 13057106718 | I56: =DATE(2025, 10, 1) -> 45931 | J56: Gabriel Khalil | K56: Gabriel Khalil
C57: BNI Keys Elite | D57: 101927 Overseas Highway, Key Largo, FL, 33037 | E57: Ernesto Dominguez | F57: Avante-NEA Insurance Group | G57: Commercial Insurance | H57: 305-648-7082 | I57: =DATE(2025, 10, 1) -> 45931 | J57: Gabriel Khalil | K57: Gabriel Khalil
C58: BNI Keys Elite | D58: 101928 Overseas Highway, Key Largo, FL, 33037 | E58: Jaclyn Kelley | F58: Better Homes and Gardens Real Estate | G58: Residential Real Estate Agent | H58: 13059231042 | I58: =DATE(2025, 10, 1) -> 45931 | J58: Gabriel Khalil | K58: Gabriel Khalil
C59: BNI Keys Elite | D59: 101929 Overseas Highway, Key Largo, FL, 33037 | E59: Lissette Romero | F59: The Florida Mortgage Lab, LLC | G59: Residential Mortgages | H59: 305-517-6323 | I59: =DATE(2025, 10, 1) -> 45931 | J59: Gabriel Khalil | K59: Gabriel Khalil
C60: BNI Keys Elite | D60: 101930 Overseas Highway, Key Largo, FL, 33037 | E60: Robert Glassmer | F60: Miami’s Best Blinds | G60: Curtains/Blinds | H60: (786) 832-6355 | I60: =DATE(2025, 10, 1) -> 45931 | J60: Gabriel Khalil | K60: Gabriel Khalil
C61: BNI Keys Elite | D61: 101931 Overseas Highway, Key Largo, FL, 33037 | E61: Sylvia Rossi-Montero | F61: Medphysion | G61: Group Benefits | H61: 305 495 6901 | I61: =DATE(2025, 10, 1) -> 45931 | J61: Gabriel Khalil | K61: Gabriel Khalil
C62: BNI Keys Elite | D62: 101932 Overseas Highway, Key Largo, FL, 33037 | E62: Teo Masters | F62: PFS Investments | G62: Finance & Insurance (Other) | H62: 3058904907 | I62: =DATE(2025, 10, 1) -> 45931 | J62: Gabriel Khalil | K62: Gabriel Khalil
C63: BNI Powerhouse | D63: 9555 SW 175th Terrace, Palmetto Bay, FL, 33157 | E63: Caleb Horvat | F63: Ameriprise Financial | G63: Financial Advisor | H63: 7864184918 | I63: =DATE(2025, 10, 1) -> 45931 | J63: Gabriel Khalil | K63: Gabriel Khalil
C64: BNI Powerhouse | D64: 9556 SW 175th Terrace, Palmetto Bay, FL, 33157 | E64: Christian Hernandez | F64: JCM Telecom LLC | G64: Telecommunications Products/Services | H64: 7867391200 | I64: =DATE(2025, 10, 1) -> 45931 | J64: Gabriel Khalil | K64: Gabriel Khalil
C65: BNI Powerhouse | D65: 9557 SW 175th Terrace, Palmetto Bay, FL, 33157 | E65: Donevan Mallard | F65: Mallard & Sharp | G65: Personal Injury Law | H65: 7864233936 | I65: =DATE(2025, 10, 1) -> 45931 | J65: Gabriel Khalil | K65: Gabriel Khalil | L65: No show
C66: BNI Powerhouse | D66: 9558 SW 175th Terrace, Palmetto Bay, FL, 33157 | E66: Eugene (Gene) La Neve | F66: La Neve Law, P.A. | G66: Elder Law | H66: 3055649499 | I66: =DATE(2025, 10, 1) -> 45931 | J66: Gabriel Khalil | K66: Gabriel Khalil
C67: BNI Powerhouse | D67: 9559 SW 175th Terrace, Palmetto Bay, FL, 33157 | E67: Ignacio Chinchilla | F67: Chinchilla Claim Services | G67: Insurance Adjuster | H67: 7863061659 | I67: =DATE(2025, 10, 1) -> 45931 | J67: Gabriel Khalil | K67: Gabriel Khalil
C68: BNI Powerhouse | D68: 9560 SW 175th Terrace, Palmetto Bay, FL, 33157 | E68: Mario W Pino | F68: Max Value Insurance Group | G68: Property & Casualty Insurance | H68: 3056691879 | I68: =DATE(2025, 10, 1) -> 45931 | J68: Gabriel Khalil | K68: Gabriel Khalil
C69: BNI Powerhouse | D69: 9561 SW 175th Terrace, Palmetto Bay, FL, 33157 | E69: Mary Portela | F69: My Buddy Bench Project | G69: Non-Profits/Fundraising Organizations | H69: 782468626 | I69: =DATE(2025, 10, 1) -> 45931 | J69: Gabriel Khalil | K69: Gabriel Khalil
C70: BNI Powerhouse | D70: 9562 SW 175th Terrace, Palmetto Bay, FL, 33157 | E70: Pedro Bobea | F70: Lux Home Construction | G70: Builder/General Contractor | H70: 305-922-8313 | I70: =DATE(2025, 10, 1) -> 45931 | J70: Gabriel Khalil | K70: Gabriel Khalil
C71: BNI Powerhouse | D71: 9563 SW 175th Terrace, Palmetto Bay, FL, 33157 | E71: Roger Snyder | F71: Coldwell Banker | G71: Residential Real Estate Agent | H71: 3059872859 | I71: =DATE(2025, 10, 1) -> 45931 | J71: Gabriel Khalil | K71: Gabriel Khalil
C72: BNI Powerhouse | D72: 9564 SW 175th Terrace, Palmetto Bay, FL, 33157 | E72: Stuart Lones | F72: Ferdie and Lones, Chartered | G72: Real Estate Law | H72: 3054453557 | I72: =DATE(2025, 10, 1) -> 45931 | J72: Gabriel Khalil | K72: Gabriel Khalil
C73: BNI Powerhouse | D73: 9565 SW 175th Terrace, Palmetto Bay, FL, 33157 | E73: YUSEF NASSALL | F73: The Mortgage Experts LLC | G73: Residential Mortgages | H73: 7864881904 | I73: =DATE(2025, 10, 1) -> 45931 | J73: Gabriel Khalil | K73: Gabriel Khalil
C74: BNI Avatar Professionals | D74: 9300 South Dadeland Blvd, Suite 200, Miami, FL, 33156 | E74: Alexander Alfonso | F74: Valiant Wealth Strategies of Miami | G74: Wealth Management | H74: 305-926-7804 | I74: =DATE(2025, 10, 1) -> 45931 | J74: Gabriel Khalil | K74: Luiz Ghiraldelli
C75: BNI Avatar Professionals | D75: 9301 South Dadeland Blvd, Suite 200, Miami, FL, 33156 | E75: Alexios Tsokos | F75: Paramount Residential Mortgage Group | G75: Residential Mortgages | H75: 9546478878 | I75: =DATE(2025, 10, 1) -> 45931 | J75: Gabriel Khalil | K75: Luiz Ghiraldelli
C76: BNI Avatar Professionals | D76: 9302 South Dadeland Blvd, Suite 200, Miami, FL, 33156 | E76: Benjamin Pepin | F76: Coral Reef Chiropractic Center | G76: Doctor/Physician | H76: 3055828461 | I76: =DATE(2025, 10, 1) -> 45931 | J76: Gabriel Khalil | K76: Luiz Ghiraldelli
C77: BNI Avatar Professionals | D77: 9303 South Dadeland Blvd, Suite 200, Miami, FL, 33156 | E77: Carlos Martorell | F77: Leading Public Adjusters | G77: Insurance Adjuster | H77: 3054905590 | I77: =DATE(2025, 10, 1) -> 45931 | J77: Gabriel Khalil | K77: Luiz Ghiraldelli
... C82: BNI Avatar Professionals | D82: 9308 South Dadeland Blvd, Suite 200, Miami, FL, 33156 | E82: Michelle Molina | F82: M3 Roofing & Construction | G82: Roofing & Gutters | H82: 305-265-5000 | I82: =DATE(2025, 10, 1) -> 45931 | J82: Gabriel Khalil | K82: Luiz Ghiraldelli
C83: BNI Avatar Professionals | D83: 9309 South Dadeland Blvd, Suite 200, Miami, FL, 33156 | E83: Monica Hanna | F83: Jhoslen Angels Inc | G83: Non-Profits/Fundraising Organizations | H83: 7864263693 | I83: =DATE(2025, 10, 1) -> 45931 | J83: Gabriel Khalil | K83: Luiz Ghiraldelli | L83: On hold
C84: BNI Avatar Professionals | D84: 9310 South Dadeland Blvd, Suite 200, Miami, FL, 33156 | E84: Rie Nakai | F84: Compass Florida LLC | G84: Residential Real Estate Agent | H84: 3057463651 | I84: =DATE(2025, 10, 1) -> 45931 | J84: Gabriel Khalil | K84: Luiz Ghiraldelli
C85: BNI Avatar Professionals | D85: 9311 South Dadeland Blvd, Suite 200, Miami, FL, 33156 | E85: Vanessa Torres | F85: Law Office of Vanessa D. Torres P.A. | G85: Family Law | H85: 786-801-0271 | I85: =DATE(2025, 10, 1) -> 45931 | J85: Gabriel Khalil | K85: Luiz Ghiraldelli
C86: BNI Avatar Professionals | D86: 9312 South Dadeland Blvd, Suite 200, Miami, FL, 33156 | E86: Xavier Schanz | F86: Five Star Painting | G86: Painter & Decorator | H86: 7862088234 | I86: =DATE(2025, 10, 1) -> 45931 | J86: Gabriel Khalil | K86: Luiz Ghiraldelli
C87: BNI Avatar Professionals | D87: 9313 South Dadeland Blvd, Suite 200, Miami, FL, 33156 | E87: Yoandry Delgado | F87: KSDT | G87: Certified Public Accountant (CPA) | H87: 3056703370 | I87: =DATE(2025, 10, 1) -> 45931 | J87: Gabriel Khalil | K87: Luiz Ghiraldelli
C88: BNI United | D88: 6200 San Amaro Dr., Coral Gables, FL, 33146 | E88: Alejandra Iglesia | F88: M2 Law Group PLLC | G88: Litigation | H88: 7865144885 | I88: =DATE(2025, 10, 1) -> 45931 | J88: Gabriel Khalil | K88: Luiz Ghiraldelli
C89: BNI United | D89: 6201 San Amaro Dr., Coral Gables, FL, 33146 | E89: Carie Negron | F89: ApexOne Realty | G89: Residential Real Estate Agent | H89: +1 (786) 808-9058 | I89: =DATE(2025, 10, 1) -> 45931 | J89: Gabriel Khalil | K89: Luiz Ghiraldelli
C90: BNI United | D90: 6202 San Amaro Dr., Coral Gables, FL, 33146 | E90: Craig Dorne | F90: Craig M Dorne PA | G90: Business Law | H90: 305-531-7890 | I90: =DATE(2025, 10, 1) -> 45931 | J90: Gabriel Khalil | K90: Luiz Ghiraldelli
C91: BNI United | D91: 6203 San Amaro Dr., Coral Gables, FL, 33146 | E91: Douglas Hiller | F91: Douglas C. Hiller Attorney at Law | G91: Real Estate Law | H91: 305-456-4607 | I91: =DATE(2025, 10, 1) -> 45931 | J91: Gabriel Khalil | K91: Luiz Ghiraldelli
C92: BNI United | D92: 6204 San Amaro Dr., Coral Gables, FL, 33146 | E92: Erick Schaefer | F92: HealthPro Consultants | G92: Health Insurance | H92: +1(305) 924-1729 | I92: =DATE(2025, 10, 1) -> 45931 | J92: Gabriel Khalil | K92: Luiz Ghiraldelli
C93: BNI United | D93: 6205 San Amaro Dr., Coral Gables, FL, 33146 | E93: Ivan Lopez | F93: Lightning Legal Courier Inc. | G93: Legal & Accounting (Other) | H93: +1 (786) 286-4167 | I93: =DATE(2025, 10, 1) -> 45931 | J93: Gabriel Khalil | K93: Luiz Ghiraldelli
C94: BNI United | D94: 6206 San Amaro Dr., Coral Gables, FL, 33146 | E94: Larry Castillo | F94: Ocean Bank | G94: Commercial Bank Services | H94: +1 (305) 926-5904 | I94: =DATE(2025, 10, 1) -> 45931 | J94: Gabriel Khalil | K94: Luiz Ghiraldelli | L94: Call Done
C95: BNI United | D95: 6207 San Amaro Dr., Coral Gables, FL, 33146 | E95: Leonardo Martinez | F95: LGM Immigration Law Firm PLLC | G95: Immigration Law | H95: +17864038958 | I95: =DATE(2025, 10, 1) -> 45931 | J95: Gabriel Khalil | K95: Luiz Ghiraldelli
C96: BNI United | D96: 6208 San Amaro Dr., Coral Gables, FL, 33146 | E96: Manny Mendez | F96: Professional Tech Solutions | G96: IT & Networks | H96: 305-677-3771 | I96: =DATE(2025, 10, 1) -> 45931 | J96: Gabriel Khalil | K96: Luiz Ghiraldelli
C97: BNI United | D97: 6209 San Amaro Dr., Coral Gables, FL, 33146 | E97: Manny Segarra | F97: Segarra & Associates PA | G97: Family Law | H97: 3,057,425,042 | I97: =DATE(2025, 10, 1) -> 45931 | J97: Gabriel Khalil | K97: Luiz Ghiraldelli
C98: BNI United | D98: 6210 San Amaro Dr., Coral Gables, FL, 33146 | E98: Pedro Chacin | F98: Pedro Chacin MBA INC DBA Coaches Financieros | G98: Life and Disability Insurance | H98: 305-332-0002 | I98: =DATE(2025, 10, 1) -> 45931 | J98: Gabriel Khalil | K98: Luiz Ghiraldelli
C99: BNI United | D99: 6211 San Amaro Dr., Coral Gables, FL, 33146 | E99: Peter Myrtetus | F99: Capital Group Funding | G99: Residential Mortgages | H99: 3057256795 | I99: =DATE(2025, 10, 1) -> 45931 | J99: Gabriel Khalil | K99: Luiz Ghiraldelli
C100: BNI United | D100: 6212 San Amaro Dr., Coral Gables, FL, 33146 | E100: Prya Murad | F100: Prya Murad Law | G100: Criminal Defense Law | H100: 8595767034 | I100: =DATE(2025, 10, 1) -> 45931 | J100: Gabriel Khalil | K100: Luiz Ghiraldelli | L100: Out of pipe
C101: BNI United | D101: 6213 San Amaro Dr., Coral Gables, FL, 33146 | E101: Sergio Fernandez | F101: Synovus Securities | G101: Financial Advisor | H101: 3054795190 | I101: =DATE(2025, 10, 1) -> 45931 | J101: Gabriel Khalil | K101: Luiz Ghiraldelli
C102: BNI United | D102: 6214 San Amaro Dr., Coral Gables, FL, 33146 | E102: Shannon Del Prado | F102: Pita Weber Del Prado | G102: Personal Injury Law | H102: 305-670-8060 | I102: =DATE(2025, 10, 1) -> 45931 | J102: Gabriel Khalil | K102: Luiz Ghiraldelli
C103: BNI United | D103: 6215 San Amaro Dr., Coral Gables, FL, 33146 | E103: Steven Dohan | F103: Dohan Certified Public Accountants | G103: Certified Public Accountant (CPA) | H103: 305-274-1367 | I103: =DATE(2025, 10, 1) -> 45931 | J103: Gabriel Khalil | K103: Luiz Ghiraldelli
C104: BNI United | D104: 6216 San Amaro Dr., Coral Gables, FL, 33146 | E104: Yailem Hernandez | F104: Del Toro Insurance | G104: Property & Casualty Insurance | H104: 3059514833 | I104: =DATE(2025, 10, 1) -> 45931 | J104: Gabriel Khalil | K104: Luiz Ghiraldelli
C105: BNI Pinnacle | D105: 2457 E Sunrise Blvd, Fort Lauderdale, FL, 33304 | E105: Adam Friedman | F105: Levin Litigation | G105: Legal & Accounting > Legal & Accounting (Other) | H105: 9546957148 | I105: =DATE(2025, 10, 1) -> 45931 | J105: Gabriel Khalil | K105: Luiz Ghiraldelli
C106: BNI Energy | D106: 7230 SW 59th Avenue, South Miami, FL, 33156 | E106: Ana Augusto | F106: Law Office of Ana C. Augusto P.A. | G106: Family Law | H106: 305-507-7655 | I106: =DATE(2025, 10, 1) -> 45931 | J106: Gabriel Khalil | K106: Luiz Ghiraldelli
C107: BNI Energy | D107: 7231 SW 59th Avenue, South Miami, FL, 33156 | E107: Armando Paz Jr | F107: Diversified Employer Benefits | G107: Life and Disability Insurance | H107: 786-306-4587 | I107: =DATE(2025, 10, 1) -> 45931 | J107: Gabriel Khalil | K107: Luiz Ghiraldelli
C108: BNI Energy | D108: 7232 SW 59th Avenue, South Miami, FL, 33156 | E108: Errol Eisinger | F108: Association Lending Services | G108: Banking Services | H108: 786-205-9842 | I108: =DATE(2025, 10, 1) -> 45931 | J108: Gabriel Khalil | K108: Luiz Ghiraldelli
C109: BNI Energy | D109: 7233 SW 59th Avenue, South Miami, FL, 33156 | E109: Jordan Francis Perez | F109: Strang Tryson PLLC | G109: Real Estate Law | H109: 3053978800 | I109: =DATE(2025, 10, 1) -> 45931 | J109: Gabriel Khalil | K109: Luiz Ghiraldelli
...

Sheet 2025.11
C6: BNI Chapter | D6: Address | E6: Member Name | F6: Company | G6: Profession | H6: Phone | I6: Contact | J6: Sales Executive | K6: SDR | L6: Status
C7: BNI Doral en Espanol | D7: Doral Contemporary Art Museum, 3450 NW 83rd Avenue, Ste 216, Doral Florida, 33166 | E7: Ana Navarro | F7: Algoritmo Agency | G7: Advertising & Marketing > Digital Marketing | H7: +17868219725 | I7: =DATE(2025, 11, 3) -> 45964 | J7: Gabriel Khalil | K7: Jonathan Oliveira
C8: BNI Doral en Espanol | D8: Doral Contemporary Art Museum, 3450 NW 83rd Avenue, Ste 216, Doral Florida, 33167 | E8: Analay Pena del Sol | F8: N/A | G8: Finance & Insurance > Insurance Adjuster | H8: 9546675939 | I8: =DATE(2025, 11, 3) -> 45964 | J8: Gabriel Khalil | K8: Jonathan Oliveira
C9: BNI Doral en Espanol | D9: Doral Contemporary Art Museum, 3450 NW 83rd Avenue, Ste 216, Doral Florida, 33168 | E9: Antonio Petruzzi | F9: Your Financial Team | G9: Finance & Insurance > Mutual Funds | H9: 3055907799 | I9: =DATE(2025, 11, 3) -> 45964 | J9: Gabriel Khalil | K9: Jonathan Oliveira
C10: BNI Doral en Espanol | D10: Doral Contemporary Art Museum, 3450 NW 83rd Avenue, Ste 216, Doral Florida, 33169 | E10: Christian Ramirez | F10: Top Tier Restoration Services | G10: Construction > Restoration | H10: 7865470307 | I10: =DATE(2025, 11, 3) -> 45964 | J10: Gabriel Khalil | K10: Jonathan Oliveira
C11: BNI Doral en Espanol | D11: Doral Contemporary Art Museum, 3450 NW 83rd Avenue, Ste 216, Doral Florida, 33170 | E11: Diana Mazud | F11: N/A | G11: Finance & Insurance > Residential Mortgages | H11: 7862874958 | I11: =DATE(2025, 11, 3) -> 45964 | J11: Gabriel Khalil | K11: Jonathan Oliveira
C12: BNI Doral en Espanol | D12: Doral Contemporary Art Museum, 3450 NW 83rd Avenue, Ste 216, Doral Florida, 33171 | E12: Elsa de Lemos | F12: Bambi International Foundation | G12: Organizations & Others > Non-Profits/Fundraising Organizations | H12: 4076831434 | I12: =DATE(2025, 11, 3) -> 45964 | J12: Gabriel Khalil | K12: Jonathan Oliveira
C13: BNI Doral en Espanol | D13: Doral Contemporary Art Museum, 3450 NW 83rd Avenue, Ste 216, Doral Florida, 33172 | E13: Elwin Manjarres | F13: Emet International Insurance LLC | G13: Finance & Insurance > Commercial Insurance | H13: 786-6140217 | I13: =DATE(2025, 11, 3) -> 45964 | J13: Gabriel Khalil | K13: Jonathan Oliveira | L13: Call Done
C14: BNI Doral en Espanol | D14: Doral Contemporary Art Museum, 3450 NW 83rd Avenue, Ste 216, Doral Florida, 33173 | E14: EUFRACIO GELVES | F14: Elite International Consultants Inc | G14: Finance & Insurance > Life and Disability Insurance | H14: 3053785210 | I14: =DATE(2025, 11, 3) -> 45964 | J14: Gabriel Khalil | K14: Jonathan Oliveira
C15: BNI Doral en Espanol | D15: Doral Contemporary Art Museum, 3450 NW 83rd Avenue, Ste 216, Doral Florida, 33174 | E15: Fayra Holguin | F15: Nexus R&C Llc | G15: Architecture & Engineering > Architecture & Engineering (Other) | H15: 7866517640 | I15: =DATE(2025, 11, 3) -> 45964 | J15: Gabriel Khalil | K15: Jonathan Oliveira
C16: BNI Doral en Espanol | D16: Doral Contemporary Art Museum, 3450 NW 83rd Avenue, Ste 216, Doral Florida, 33175 | E16: Francisco Hernadez | F16: Dr.Be | G16: Health & Wellness > Chiropractor | H16: +17864938102 | I16: =DATE(2025, 11, 3) -> 45964 | J16: Gabriel Khalil | K16: Jonathan Oliveira
C17: BNI Doral en Espanol | D17: Doral Contemporary Art Museum, 3450 NW 83rd Avenue, Ste 216, Doral Florida, 33176 | E17: Giselle Oviedo | F17: KUNAK USA LLC | G17: Computer & Programming > IT & Networks | H17: +13057732718 | I17: =DATE(2025, 11, 3) -> 45964 | J17: Gabriel Khalil | K17: Jonathan Oliveira
C18: BNI Doral en Espanol | D18: Doral Contemporary Art Museum, 3450 NW 83rd Avenue, Ste 216, Doral Florida, 33177 | E18: Gregory Saldamando | F18: First Stop Legal | G18: Legal & Accounting > Legal & Accounting (Other) | H18: (786) 498-2210 | I18: =DATE(2025, 11, 3) -> 45964 | J18: Gabriel Khalil | K18: Jonathan Oliveira
C19: BNI Doral en Espanol | D19: Doral Contemporary Art Museum, 3450 NW 83rd Avenue, Ste 216, Doral Florida, 33178 | E19: Jacqueline Gonzalez | F19: JP Morgan private bank | G19: Finance & Insurance > Wealth Management | H19: 305347008 | I19: =DATE(2025, 11, 3) -> 45964 | J19: Gabriel Khalil | K19: Jonathan Oliveira
C20: BNI Doral en Espanol | D20: Doral Contemporary Art Museum, 3450 NW 83rd Avenue, Ste 216, Doral Florida, 33179 | E20: Jimmy Arenas | F20: Mkaddesh Insurance & Financial Corp | G20: Finance & Insurance > Health Insurance | H20: 7867974310 | I20: =DATE(2025, 11, 3) -> 45964 | J20: Gabriel Khalil | K20: Jonathan Oliveira
C21: BNI Doral en Espanol | D21: Doral Contemporary Art Museum, 3450 NW 83rd Avenue, Ste 216, Doral Florida, 33180 | E21: Karla Lopez-Fernandez | F21: Law Office of Karla Lopez-Fernandez | G21: Legal & Accounting > Personal Injury Law | H21: (305)517-1116 | I21: =DATE(2025, 11, 3) -> 45964 | J21: Gabriel Khalil | K21: Jonathan Oliveira
C22: BNI Doral en Espanol | D22: Doral Contemporary Art Museum, 3450 NW 83rd Avenue, Ste 216, Doral Florida, 33181 | E22: LORRAINE PEREZ | F22: INTERCONTINENTAL LAW FIRM | G22: Legal & Accounting > Immigration Law | H22: +3054441272 | I22: =DATE(2025, 11, 3) -> 45964 | J22: Gabriel Khalil | K22: Jonathan Oliveira
C23: BNI Doral en Espanol | D23: Doral Contemporary Art Museum, 3450 NW 83rd Avenue, Ste 216, Doral Florida, 33182 | E23: LUZ SANCHEZ | F23: BUSINESS TIPS & ADVISORY SERVICES INC | G23: Legal & Accounting > Accounting Services | H23: 7865855929 | I23: =DATE(2025, 11, 3) -> 45964 | J23: Gabriel Khalil | K23: Jonathan Oliveira
C24: BNI Doral en Espanol | D24: Doral Contemporary Art Museum, 3450 NW 83rd Avenue, Ste 216, Doral Florida, 33183 | E24: Moises Benoliel | F24: Benoliel Consulting & Solutions LLC | G24: Real Estate Services > Real Estate Inspector | H24: 3058773711 | I24: =DATE(2025, 11, 3) -> 45964 | J24: Gabriel Khalil | K24: Jonathan Oliveira
C25: BNI Doral en Espanol | D25: Doral Contemporary Art Museum, 3450 NW 83rd Avenue, Ste 216, Doral Florida, 33184 | E25: Orestes Garcia | F25: Ayala Law | G25: Legal & Accounting > Litigation | H25: 7862104861 | I25: =DATE(2025, 11, 3) -> 45964 | J25: Gabriel Khalil | K25: Jonathan Oliveira
C26: BNI Doral en Espanol | D26: Doral Contemporary Art Museum, 3450 NW 83rd Avenue, Ste 216, Doral Florida, 33185 | E26: Ramón Rodríguez | F26: Avanti Way Realty | G26: Real Estate Services > Residential Real Estate Agent | H26: +13054975435 | I26: =DATE(2025, 11, 3) -> 45964 | J26: Gabriel Khalil | K26: Jonathan Oliveira
C27: BNI Doral en Espanol | D27: Doral Contemporary Art Museum, 3450 NW 83rd Avenue, Ste 216, Doral Florida, 33186 | E27: Ronald Dell'acqua | F27: Fotografo | G27: Advertising & Marketing > Photographer | H27: 7862141480 | I27: =DATE(2025, 11, 3) -> 45964 | J27: Gabriel Khalil | K27: Jonathan Oliveira
C28: BNI Doral en Espanol | D28: Doral Contemporary Art Museum, 3450 NW 83rd Avenue, Ste 216, Doral Florida, 33187 | E28: Susana Grant | F28: Folio Title LLC | G28: Real Estate Services > Title Services | H28: 3057789684 | I28: =DATE(2025, 11, 3) -> 45964 | J28: Gabriel Khalil | K28: Jonathan Oliveira
C29: BNI Doral Excellences | D29: Waterford District, 6505 Waterford District Drive, Ste 108 Miami, Florida, 33126 | E29: Alberto Diaz | F29: MOR Lending | G29: Finance & Insurance > Residential Mortgages | H29: 7862394998 | I29: =DATE(2025, 11, 3) -> 45964 | J29: Gabriel Khalil | K29: Jonathan Oliveira
C30: BNI Doral Excellences | D30: Waterford District, 6505 Waterford District Drive, Ste 108 Miami, Florida, 33127 | E30: Ana Paredes | F30: ABP Accounting | G30: Legal & Accounting > Accounting Services | H30: 786-477-3028 | I30: =DATE(2025, 11, 3) -> 45964 | J30: Gabriel Khalil | K30: Jonathan Oliveira
C31: BNI Doral Excellences | D31: Waterford District, 6505 Waterford District Drive, Ste 108 Miami, Florida, 33128 | E31: Bibiana Martorell | F31: Estrella insurance | G31: Finance & Insurance > Property & Casualty Insurance | H31: 3056449301 | I31: =DATE(2025, 11, 3) -> 45964 | J31: Gabriel Khalil | K31: Jonathan Oliveira
C32: BNI Doral Excellences | D32: Waterford District, 6505 Waterford District Drive, Ste 108 Miami, Florida, 33129 | E32: Christopher Rivas | F32: T&S Impact Windows & Doors | G32: Construction > Windows & Doors | H32: 786-223-5502 | I32: =DATE(2025, 11, 3) -> 45964 | J32: Gabriel Khalil | K32: Jonathan Oliveira
C33: BNI Doral Excellences | D33: Waterford District, 6505 Waterford District Drive, Ste 108 Miami, Florida, 33130 | E33: Gabriel Quiroga | F33: Compass | G33: Real Estate Services > Residential Real Estate Agent | H33: +17862345780 | I33: =DATE(2025, 11, 3) -> 45964 | J33: Gabriel Khalil | K33: Jonathan Oliveira
C34: BNI Doral Excellences | D34: Waterford District, 6505 Waterford District Drive, Ste 108 Miami, Florida, 33131 | E34: Jesus Lara | F34: New York Life | G34: Finance & Insurance > Life and Disability Insurance | H34: 3057932567 | I34: =DATE(2025, 11, 3) -> 45964 | J34: Gabriel Khalil | K34: Jonathan Oliveira | L34: No show
C35: BNI Doral Excellences | D35: Waterford District, 6505 Waterford District Drive, Ste 108 Miami, Florida, 33132 | E35: Jose Garcia | F35: UBS Financial Services | G35: Finance & Insurance > Financial Advisor | H35: 305-733-3771 | I35: =DATE(2025, 11, 3) -> 45964 | J35: Gabriel Khalil | K35: Jonathan Oliveira
C36: BNI Doral Excellences | D36: Waterford District, 6505 Waterford District Drive, Ste 108 Miami, Florida, 33133 | E36: Kevin Spencer | F36: Rod Plus Technology LLC | G36: Computer & Programming > IT & Networks | H36: 3058593035 | I36: =DATE(2025, 11, 3) -> 45964 | J36: Gabriel Khalil | K36: Jonathan Oliveira | L36: No show
C37: BNI Doral Excellences | D37: Waterford District, 6505 Waterford District Drive, Ste 108 Miami, Florida, 33134 | E37: Ricardo Rodriguez | F37: Rodriguez Law PL | G37: Legal & Accounting > Litigation | H37: 305-262-8226 | I37: =DATE(2025, 11, 3) -> 45964 | J37: Gabriel Khalil | K37: Jonathan Oliveira
C38: BNI Doral Excellences | D38: Waterford District, 6505 Waterford District Drive, Ste 108 Miami, Florida, 33135 | E38: Stephen Guerrero | F38: Guerrero Law Group PLLC | G38: Legal & Accounting > Estate Planning Law | H38: (305) 488-6250 | I38: =DATE(2025, 11, 3) -> 45964 | J38: Gabriel Khalil | K38: Jonathan Oliveira
C39: BNI Doral Excellences | D39: Waterford District, 6505 Waterford District Drive, Ste 108 Miami, Florida, 33136 | E39: Sunem Herrera | F39: The Herrera Insurance Group | G39: Finance & Insurance > Commercial Insurance | H39: 305-264-0177 | I39: =DATE(2025, 11, 3) -> 45964 | J39: Gabriel Khalil | K39: Jonathan Oliveira
C40: BNI Doral Excellences | D40: Waterford District, 6505 Waterford District Drive, Ste 108 Miami, Florida, 33137 | E40: Tongelah Webster | F40: City Permit | G40: Construction > Construction (Other) | H40: 305-908-1142 | I40: =DATE(2025, 11, 3) -> 45964 | J40: Gabriel Khalil | K40: Jonathan Oliveira
C41: BNI Lux Connect | D41: Industrious Lincoln Road, 350 Lincoln Rd 3rd Floor, Miami Beach, Florida, 33139 | E41: Agustina Valdovinos | F41: N/A | G41: Real Estate Services > Title Services | H41: 9542929759 | I41: =DATE(2025, 11, 3) -> 45964 | J41: Gabriel Khalil | K41: Jonathan Oliveira
C42: BNI Lux Connect | D42: Industrious Lincoln Road, 350 Lincoln Rd 3rd Floor, Miami Beach, Florida, 33140 | E42: Alexandra Almanza | F42: Socially Mavs | G42: Advertising & Marketing > Advertising & Marketing (Other) | H42: 786) 867-8861 | I42: =DATE(2025, 11, 3) -> 45964 | J42: Gabriel Khalil | K42: Jonathan Oliveira
C43: BNI Lux Connect | D43: Industrious Lincoln Road, 350 Lincoln Rd 3rd Floor, Miami Beach, Florida, 33141 | E43: Attila Yildiz | F43: Coldwell Banker | G43: Real Estate Services > Residential Real Estate Agent | H43: 786-333-3727 | I43: =DATE(2025, 11, 3) -> 45964 | J43: Gabriel Khalil | K43: Jonathan Oliveira
C44: BNI Lux Connect | D44: Industrious Lincoln Road, 350 Lincoln Rd 3rd Floor, Miami Beach, Florida, 33142 | E44: Bernard Cohen | F44: UBS | G44: Finance & Insurance > Financial Advisor | H44: 212-626-8712 | I44: =DATE(2025, 11, 3) -> 45964 | J44: Gabriel Khalil | K44: Jonathan Oliveira
C45: BNI Lux Connect | D45: Industrious Lincoln Road, 350 Lincoln Rd 3rd Floor, Miami Beach, Florida, 33143 | E45: Chris Cooney | F45: Affinity Management Services | G45: Real Estate Services > Property Management | H45: 305-619-5663 | I45: =DATE(2025, 11, 3) -> 45964 | J45: Gabriel Khalil | K45: Jonathan Oliveira
C46: BNI Lux Connect | D46: Industrious Lincoln Road, 350 Lincoln Rd 3rd Floor, Miami Beach, Florida, 33144 | E46: Chris Romeu | F46: Prestige Audio Visual International | G46: Construction > Construction (Other) | H46: N/A | I46: =DATE(2025, 11, 3) -> 45964 | J46: Gabriel Khalil | K46: Jonathan Oliveira
C47: BNI Lux Connect | D47: Industrious Lincoln Road, 350 Lincoln Rd 3rd Floor, Miami Beach, Florida, 33145 | E47: Christian Peter II | F47: N/A | G47: Real Estate Services > Commercial Real Estate | H47: 3059873053 | I47: =DATE(2025, 11, 3) -> 45964 | J47: Gabriel Khalil | K47: Jonathan Oliveira
C48: BNI Lux Connect | D48: Industrious Lincoln Road, 350 Lincoln Rd 3rd Floor, Miami Beach, Florida, 33146 | E48: Christina Specos | F48: Specos Enterprises LLC | G48: Health & Wellness > Massage Therapist | H48: 6093200075 | I48: =DATE(2025, 11, 3) -> 45964 | J48: Gabriel Khalil | K48: Jonathan Oliveira
C49: BNI Lux Connect | D49: Industrious Lincoln Road, 350 Lincoln Rd 3rd Floor, Miami Beach, Florida, 33147 | E49: Christopher Solis | F49: KSDT | G49: Legal & Accounting > Certified Public Accountant (CPA) | H49: 3054961099 | I49: =DATE(2025, 11, 3) -> 45964 | J49: Gabriel Khalil | K49: Jonathan Oliveira
C50: BNI Lux Connect | D50: Industrious Lincoln Road, 350 Lincoln Rd 3rd Floor, Miami Beach, Florida, 33148 | E50: David Nudel | F50: Rafuls Law Group | G50: Legal & Accounting > Legal & Accounting (Other) | H50: 3057783068 | I50: =DATE(2025, 11, 3) -> 45964 | J50: Gabriel Khalil | K50: Jonathan Oliveira
C51: BNI Lux Connect | D51: Industrious Lincoln Road, 350 Lincoln Rd 3rd Floor, Miami Beach, Florida, 33149 | E51: El-Genesis Bey | F51: EGB Wellness Solutions | G51: Health & Wellness > Alternative Wellness | H51: 3058497580 | I51: =DATE(2025, 11, 3) -> 45964 | J51: Gabriel Khalil | K51: Jonathan Oliveira
C52: BNI Lux Connect | D52: Industrious Lincoln Road, 350 Lincoln Rd 3rd Floor, Miami Beach, Florida, 33150 | E52: Eli Sklarin | F52: Alive & Wealth | G52: Finance & Insurance > Life and Disability Insurance | H52: 2018354622 | I52: =DATE(2025, 11, 3) -> 45964 | J52: Gabriel Khalil | K52: Jonathan Oliveira
C53: BNI Lux Connect | D53: Industrious Lincoln Road, 350 Lincoln Rd 3rd Floor, Miami Beach, Florida, 33151 | E53: Emanuele Liccardo | F53: Puremancare.com | G53: Personal Services > Hair Stylist | H53: 7862168754 | I53: =DATE(2025, 11, 3) -> 45964 | J53: Gabriel Khalil | K53: Jonathan Oliveira | L53: Call Done
C54: BNI Lux Connect | D54: Industrious Lincoln Road, 350 Lincoln Rd 3rd Floor, Miami Beach, Florida, 33152 | E54: Felipe Ossana | F54: UP TO THE ROOF | G54: Construction > Roofing & Gutters | H54: 7862109698 | I54: =DATE(2025, 11, 3) -> 45964 | J54: Gabriel Khalil | K54: Jonathan Oliveira
C55: BNI Lux Connect | D55: Industrious Lincoln Road, 350 Lincoln Rd 3rd Floor, Miami Beach, Florida, 33153 | E55: Gabriel Alejandro Albelo | F55: South Beach Apostille Translation and Notary | G55: Legal & Accounting > Notary | H55: 7869700450 | I55: =DATE(2025, 11, 3) -> 45964 | J55: Gabriel Khalil | K55: Jonathan Oliveira
C56: BNI Lux Connect | D56: Industrious Lincoln Road, 350 Lincoln Rd 3rd Floor, Miami Beach, Florida, 33154 | E56: George Milian | F56: Rely On Solar South Florida LLC | G56: Consulting > Energy Consulting | H56: 305-744-1200 | I56: =DATE(2025, 11, 3) -> 45964 | J56: Gabriel Khalil | K56: Jonathan Oliveira
C57: BNI Lux Connect | D57: Industrious Lincoln Road, 350 Lincoln Rd 3rd Floor, Miami Beach, Florida, 33155 | E57: Ivan Botero | F57: Rapid Public Adjusters | G57: Finance & Insurance > Finance & Insurance (Other) | H57: 3055620320 | I57: =DATE(2025, 11, 3) -> 45964 | J57: Gabriel Khalil | K57: Jonathan Oliveira
C58: BNI Lux Connect | D58: Industrious Lincoln Road, 350 Lincoln Rd 3rd Floor, Miami Beach, Florida, 33156 | E58: Johnny Falco | F58: Biomonde | G58: Real Estate Services > Window Cleaning | H58: 728-500-9070 | I58: =DATE(2025, 11, 3) -> 45964 | J58: Gabriel Khalil | K58: Jonathan Oliveira
C59: BNI Lux Connect | D59: Industrious Lincoln Road, 350 Lincoln Rd 3rd Floor, Miami Beach, Florida, 33157 | E59: Juan Babani | F59: Cornerstone First Mortgage | G59: Finance & Insurance > Residential Mortgages | H59: 3059156625 | I59: =DATE(2025, 11, 3) -> 45964 | J59: Gabriel Khalil | K59: Jonathan Oliveira
C60: BNI Lux Connect | D60: Industrious Lincoln Road, 350 Lincoln Rd 3rd Floor, Miami Beach, Florida, 33158 | E60: Kirra Sherman | F60: Expand your Mind LLC | G60: Consulting > Consulting (Other) | H60: 3106069559 | I60: =DATE(2025, 11, 3) -> 45964 | J60: Gabriel Khalil | K60: Jonathan Oliveira
C61: BNI Lux Connect | D61: Industrious Lincoln Road, 350 Lincoln Rd 3rd Floor, Miami Beach, Florida, 33159 | E61: Kyle Savage | F61: Vibe Haus Collective | G61: Event & Business Service > Event Planner | H61: 631-334-9611 | I61: =DATE(2025, 11, 3) -> 45964 | J61: Gabriel Khalil | K61: Jonathan Oliveira
C62: BNI Lux Connect | D62: Industrious Lincoln Road, 350 Lincoln Rd 3rd Floor, Miami Beach, Florida, 33160 | E62: Maybelline Jerez | F62: Vita Curated | G62: Event & Business Service > Event Planner | H62: 917-7366573 | I62: =DATE(2025, 11, 3) -> 45964 | J62: Gabriel Khalil | K62: Jonathan Oliveira
C63: BNI Lux Connect | D63: Industrious Lincoln Road, 350 Lincoln Rd 3rd Floor, Miami Beach, Florida, 33161 | E63: Mendel Raksin | F63: P&G Insurance Brokers | G63: Finance & Insurance > Insurance Broker | H63: 3475466746 | I63: =DATE(2025, 11, 3) -> 45964 | J63: Gabriel Khalil | K63: Jonathan Oliveira
C64: BNI Lux Connect | D64: Industrious Lincoln Road, 350 Lincoln Rd 3rd Floor, Miami Beach, Florida, 33162 | E64: Mia Dequine | F64: Acupuncture by Mia (Mia Dequine LLC) | G64: Health & Wellness > Acupuncture | H64: 305-610-2299 | I64: =DATE(2025, 11, 3) -> 45964 | J64: Gabriel Khalil | K64: Jonathan Oliveira
C65: BNI Lux Connect | D65: Industrious Lincoln Road, 350 Lincoln Rd 3rd Floor, Miami Beach, Florida, 33163 | E65: Nick Gelpi | F65: Gelpi projects | G65: Architecture & Engineering > Architect | H65: 6464105168 | I65: =DATE(2025, 11, 3) -> 45964 | J65: Gabriel Khalil | K65: Jonathan Oliveira
C66: BNI Lux Connect | D66: Industrious Lincoln Road, 350 Lincoln Rd 3rd Floor, Miami Beach, Florida, 33164 | E66: Nicole Boswell | F66: US Health Advisors | G66: Finance & Insurance > Health Insurance | H66: 3055102703 | I66: =DATE(2025, 11, 3) -> 45964 | J66: Gabriel Khalil | K66: Jonathan Oliveira
C67: BNI Lux Connect | D67: Industrious Lincoln Road, 350 Lincoln Rd 3rd Floor, Miami Beach, Florida, 33165 | E67: Oscar A Campos | F67: N/A | G67: Legal & Accounting > Litigation | H67: 9546497557 | I67: =DATE(2025, 11, 3) -> 45964 | J67: Gabriel Khalil | K67: Jonathan Oliveira
C68: BNI Lux Connect | D68: Industrious Lincoln Road, 350 Lincoln Rd 3rd Floor, Miami Beach, Florida, 33166 | E68: Richard Ramirez | F68: Home Image BUILDERS | G68: Construction > Builder/General Contractor | H68: 7867997779 | I68: =DATE(2025, 11, 3) -> 45964 | J68: Gabriel Khalil | K68: Jonathan Oliveira
C69: BNI Lux Connect | D69: Industrious Lincoln Road, 350 Lincoln Rd 3rd Floor, Miami Beach, Florida, 33167 | E69: Rudy Gonzalez | F69: Motor Breeze | G69: Car & Motorcycle > Auto/Car Sales | H69: 3052440709 | I69: =DATE(2025, 11, 3) -> 45964 | J69: Gabriel Khalil | K69: Jonathan Oliveira
C70: BNI Lux Connect | D70: Industrious Lincoln Road, 350 Lincoln Rd 3rd Floor, Miami Beach, Florida, 33168 | E70: Stephanie Tatem | F70: https://www.tateminteriors.com | G70: Construction > Interior Design | H70: (305) 399-9791 | I70: =DATE(2025, 11, 3) -> 45964 | J70: Gabriel Khalil | K70: Jonathan Oliveira
C71: BNI Lux Connect | D71: Industrious Lincoln Road, 350 Lincoln Rd 3rd Floor, Miami Beach, Florida, 33169 | E71: Thomas Graham | F71: Mausner Graham Injury Law PLLC | G71: Legal & Accounting > Personal Injury Law | H71: 14122150369 | I71: =DATE(2025, 11, 3) -> 45964 | J71: Gabriel Khalil | K71: Jonathan Oliveira
C72: BNI Lux Connect | D72: Industrious Lincoln Road, 350 Lincoln Rd 3rd Floor, Miami Beach, Florida, 33170 | E72: Vanessa Jencks | F72: ByteBlink AI | G72: Advertising & Marketing > Marketing Consultant | H72: +18648375643 | I72: =DATE(2025, 11, 3) -> 45964 | J72: Gabriel Khalil | K72: Jonathan Oliveira
C73: BNI Lux Connect | D73: Industrious Lincoln Road, 350 Lincoln Rd 3rd Floor, Miami Beach, Florida, 33171 | E73: Victor Gonzalez | F73: City National Bank | G73: Finance & Insurance > Banking Services | H73: 7866024923 | I73: =DATE(2025, 11, 3) -> 45964 | J73: Gabriel Khalil | K73: Jonathan Oliveira
C74: BNI Lux Connect | D74: Industrious Lincoln Road, 350 Lincoln Rd 3rd Floor, Miami Beach, Florida, 33172 | E74: Yesis Gomez | F74: Allstate Insurance_ YRG Insurance Pro | G74: Finance & Insurance > Property & Casualty Insurance | H74: 7867039914 | I74: =DATE(2025, 11, 3) -> 45964 | J74: Gabriel Khalil | K74: Jonathan Oliveira
C75: BNI Lux Connect | D75: Industrious Lincoln Road, 350 Lincoln Rd 3rd Floor, Miami Beach, Florida, 33173 | E75: Zach Simpson | F75: The General Counsel Law Firm | G75: Legal & Accounting > Business Law | H75: +18643630222 | I75: =DATE(2025, 11, 3) -> 45964 | J75: Gabriel Khalil | K75: Jonathan Oliveira
C76: BNI Pioneers | D76: Moxy Miami South Beach, 915 Washington Avenue, Miami Beach, Florida, 33139 | E76: Aaron Talone | F76: AllStar Insurance Services Inc. | G76: Finance & Insurance > Property & Casualty Insurance | H76: 3059988850 | I76: =DATE(2025, 11, 3) -> 45964 | J76: Gabriel Khalil | K76: Jonathan Oliveira
C77: BNI Pioneers | D77: Moxy Miami South Beach, 915 Washington Avenue, Miami Beach, Florida, 33140 | E77: Alec Ross | F77: The Trademark Place | G77: Legal & Accounting > Intellectual Property Law | H77: 305-791-7218 | I77: =DATE(2025, 11, 3) -> 45964 | J77: Gabriel Khalil | K77: Jonathan Oliveira
C78: BNI Pioneers | D78: Moxy Miami South Beach, 915 Washington Avenue, Miami Beach, Florida, 33141 | E78: Anne-Christine Carrie | F78: Miami 21 Zoning and Entitlements | G78: Real Estate Services > Real Estate Planning Consultant | H78: 9542045452 | I78: =DATE(2025, 11, 3) -> 45964 | J78: Gabriel Khalil | K78: Jonathan Oliveira
C79: BNI Pioneers | D79: Moxy Miami South Beach, 915 Washington Avenue, Miami Beach, Florida, 33142 | E79: Arturo Moquete | F79: BankUnited | G79: Finance & Insurance > Banking Services | H79: +12014671641 | I79: =DATE(2025, 11, 3) -> 45964 | J79: Gabriel Khalil | K79: Jonathan Oliveira
C80: BNI Pioneers | D80: Moxy Miami South Beach, 915 Washington Avenue, Miami Beach, Florida, 33143 | E80: Brian Gordon | F80: Shell Lumber & Hardware | G80: Retail > Building Materials Retail | H80: 954-205-2254 | I80: =DATE(2025, 11, 3) -> 45964 | J80: Gabriel Khalil | K80: Jonathan Oliveira
C81: BNI Pioneers | D81: Moxy Miami South Beach, 915 Washington Avenue, Miami Beach, Florida, 33144 | E81: Bryan Sherman | F81: Sherman Law Firm | G81: Legal & Accounting > Litigation | H81: 3059928815 | I81: =DATE(2025, 11, 3) -> 45964 | J81: Gabriel Khalil | K81: Jonathan Oliveira
C82: BNI Pioneers | D82: Moxy Miami South Beach, 915 Washington Avenue, Miami Beach, Florida, 33145 | E82: Dana Goldman | F82: Dana Goldman | G82: Legal & Accounting > Real Estate Law | H82: 3053080040 | I82: =DATE(2025, 11, 3) -> 45964 | J82: Gabriel Khalil | K82: Jonathan Oliveira
C83: BNI Pioneers | D83: Moxy Miami South Beach, 915 Washington Avenue, Miami Beach, Florida, 33146 | E83: Ellen Mitchel | F83: RE/MAX Allstars | G83: Real Estate Services > Residential Real Estate Agent | H83: 954-292-6412 | I83: =DATE(2025, 11, 3) -> 45964 | J83: Gabriel Khalil | K83: Jonathan Oliveira
C84: BNI Pioneers | D84: Moxy Miami South Beach, 915 Washington Avenue, Miami Beach, Florida, 33147 | E84: Eric Mausner | F84: Mausner Graham Injury Law PLLC | G84: Legal & Accounting > Personal Injury Law | H84: 305-344-4878 | I84: =DATE(2025, 11, 3) -> 45964 | J84: Gabriel Khalil | K84: Jonathan Oliveira
C85: BNI Pioneers | D85: Moxy Miami South Beach, 915 Washington Avenue, Miami Beach, Florida, 33148 | E85: GASTON R CORTES | F85: CORTES ACCOUNTING & ASSOCIATES LLC | G85: Legal & Accounting > Certified Public Accountant (CPA) | H85: 13059011404 | I85: =DATE(2025, 11, 3) -> 45964 | J85: Gabriel Khalil | K85: Jonathan Oliveira
C86: BNI Pioneers | D86: Moxy Miami South Beach, 915 Washington Avenue, Miami Beach, Florida, 33149 | E86: Jabir Najair | F86: Riajan Mortgage | G86: Finance & Insurance > Residential Mortgages | H86: 305-680-5400 | I86: =DATE(2025, 11, 3) -> 45964 | J86: Gabriel Khalil | K86: Jonathan Oliveira
C87: BNI Pioneers | D87: Moxy Miami South Beach, 915 Washington Avenue, Miami Beach, Florida, 33150 | E87: Jasmine Glover | F87: Lowell Newman | G87: Finance & Insurance > Financial Advisor | H87: 6789336817 | I87: =DATE(2025, 11, 3) -> 45964 | J87: Gabriel Khalil | K87: Jonathan Oliveira
C88: BNI Pioneers | D88: Moxy Miami South Beach, 915 Washington Avenue, Miami Beach, Florida, 33151 | E88: Jeffrey Nissani | F88: N/A | G88: Finance & Insurance > Health Insurance | H88: (917) 776 6650 | I88: =DATE(2025, 11, 3) -> 45964 | J88: Gabriel Khalil | K88: Jonathan Oliveira
C89: BNI Pioneers | D89: Moxy Miami South Beach, 915 Washington Avenue, Miami Beach, Florida, 33152 | E89: Jeffrey Sharmat | F89: North Star Real Estate Advisors | G89: Real Estate Services > Commercial Real Estate | H89: 305439-7070 | I89: =DATE(2025, 11, 3) -> 45964 | J89: Gabriel Khalil | K89: Jonathan Oliveira
C90: BNI Pioneers | D90: Moxy Miami South Beach, 915 Washington Avenue, Miami Beach, Florida, 33153 | E90: Jose Oldenburg | F90: J.D. Oldenburg Corp | G90: Advertising & Marketing > Videographer/Film Producer | H90: 9543306358 | I90: =DATE(2025, 11, 3) -> 45964 | J90: Gabriel Khalil | K90: Jonathan Oliveira | L90: Call Done
C91: BNI Pioneers | D91: Moxy Miami South Beach, 915 Washington Avenue, Miami Beach, Florida, 33154 | E91: Julia Cole | F91: Julia L. Cole | G91: Health & Wellness > Counselor/Psychotherapist | H91: 9142990464 | I91: =DATE(2025, 11, 3) -> 45964 | J91: Gabriel Khalil | K91: Jonathan Oliveira
C92: BNI Pioneers | D92: Moxy Miami South Beach, 915 Washington Avenue, Miami Beach, Florida, 33155 | E92: Mark Zuckier | F92: Five Star Painting | G92: Construction > Painter & Decorator | H92: (786) 575-0425 | I92: =DATE(2025, 11, 3) -> 45964 | J92: Gabriel Khalil | K92: Jonathan Oliveira
C93: BNI Pioneers | D93: Moxy Miami South Beach, 915 Washington Avenue, Miami Beach, Florida, 33156 | E93: Owen Carhart | F93: Business Optimization Group | G93: Consulting > Business Consultant | H93: 786-558-6058 | I93: =DATE(2025, 11, 3) -> 45964 | J93: Gabriel Khalil | K93: Jonathan Oliveira
C94: BNI Pioneers | D94: Moxy Miami South Beach, 915 Washington Avenue, Miami Beach, Florida, 33157 | E94: Sacha Awwa | F94: Sacha Awwa Marketing Group | G94: Advertising & Marketing > Digital Marketing | H94: 19177145541 | I94: =DATE(2025, 11, 3) -> 45964 | J94: Gabriel Khalil | K94: Jonathan Oliveira
C95: BNI Pioneers | D95: Moxy Miami South Beach, 915 Washington Avenue, Miami Beach, Florida, 33158 | E95: Steven Schwartz | F95: Steven K. Schwartz PA | G95: Legal & Accounting > Elder Law | H95: 305-563-2739 | I95: =DATE(2025, 11, 3) -> 45964 | J95: Gabriel Khalil | K95: Jonathan Oliveira
C96: BNI Pioneers | D96: Moxy Miami South Beach, 915 Washington Avenue, Miami Beach, Florida, 33159 | E96: Valter Bombonato | F96: Renovation Sells Miami | G96: Construction > Renovations/Remodeling | H96: +1 (786) 647-5011 | I96: =DATE(2025, 11, 3) -> 45964 | J96: Gabriel Khalil | K96: Jonathan Oliveira
C97: BNI Pioneers | D97: Moxy Miami South Beach, 915 Washington Avenue, Miami Beach, Florida, 33160 | E97: Winston Cuenant | F97: Cuenant & Nazareth | G97: Legal & Accounting > Bankruptcy Law | H97: (954)766-4271 | I97: =DATE(2025, 11, 3) -> 45964 | J97: Gabriel Khalil | K97: Jonathan Oliveira
C98: BNI Downtown Miami | D98: The Hub @Office Logic, 1501 Biscayne Blvd, Ste 501, Miami, FL, 33132 | E98: Alexander Jackson | F98: Private Lending | G98: Finance & Insurance > Personal Loans | H98: (786) 514-5186 | I98: =DATE(2025, 11, 3) -> 45964 | J98: Gabriel Khalil | K98: Jonathan Oliveira
C99: BNI Downtown Miami | D99: The Hub @Office Logic, 1501 Biscayne Blvd, Ste 501, Miami, FL, 33133 | E99: Daniel Marrugo | F99: Score Pro Financial LLC | G99: Finance & Insurance > Credit Repair | H99: +1 (786) 381-5263 | I99: =DATE(2025, 11, 3) -> 45964 | J99: Gabriel Khalil | K99: Jonathan Oliveira
C100: BNI Downtown Miami | D100: The Hub @Office Logic, 1501 Biscayne Blvd, Ste 501, Miami, FL, 33134 | E100: Giancarlo Victorero | F100: GiaVic Consulting | G100: Legal & Accounting > Accounting Services | H100: 3053109042 | I100: =DATE(2025, 11, 3) -> 45964 | J100: Gabriel Khalil | K100: Jonathan Oliveira
C101: BNI Downtown Miami | D101: The Hub @Office Logic, 1501 Biscayne Blvd, Ste 501, Miami, FL, 33135 | E101: Gregory Bianco | F101: P.A. | G101: Legal & Accounting > Legal & Accounting (Other) | H101: 3053353407 | I101: =DATE(2025, 11, 3) -> 45964 | J101: Gabriel Khalil | K101: Jonathan Oliveira
C102: BNI Downtown Miami | D102: The Hub @Office Logic, 1501 Biscayne Blvd, Ste 501, Miami, FL, 33136 | E102: Jennifer Panchi | F102: Weichert Realtors Rev Group | G102: Real Estate Services > Residential Real Estate Agent | H102: 954-487-0119 | I102: =DATE(2025, 11, 3) -> 45964 | J102: Gabriel Khalil | K102: Jonathan Oliveira
C103: BNI Downtown Miami | D103: The Hub @Office Logic, 1501 Biscayne Blvd, Ste 501, Miami, FL, 33137 | E103: Justin Guido | F103: Mausner Graham Injury Firm | G103: Legal & Accounting > Personal Injury Law | H103: 9144949211 | I103: =DATE(2025, 11, 3) -> 45964 | J103: Gabriel Khalil | K103: Jonathan Oliveira
C104: BNI Downtown Miami | D104: The Hub @Office Logic, 1501 Biscayne Blvd, Ste 501, Miami, FL, 33138 | E104: Marcel Garcia | F104: The Mortgage Link | G104: Finance & Insurance > Residential Mortgages | H104: 248-890-7255 | I104: =DATE(2025, 11, 3) -> 45964 | J104: Gabriel Khalil | K104: Jonathan Oliveira
C105: BNI Downtown Miami | D105: The Hub @Office Logic, 1501 Biscayne Blvd, Ste 501, Miami, FL, 33139 | E105: Martin Canada | F105: ADP | G105: Legal & Accounting > Payroll Service | H105: 7863525044 | I105: =DATE(2025, 11, 3) -> 45964 | J105: Gabriel Khalil | K105: Jonathan Oliveira
...
